Metadata-Version: 2.1
Name: jk-simpleobjpersistency
Version: 0.2021.1.18
Summary: This python module provides a simple persistency for data objects.
Home-page: UNKNOWN
Author: Jürgen Knauth
Author-email: pubsrc@binary-overflow.de
License: proprietary
Platform: UNKNOWN
Classifier: Development Status :: 5 - Production/Stable
Classifier: Programming Language :: Python :: 3
